phiphadl/TestingPipeline.py
phiphadl/TrainingPipeline.py
phiphadl/__init__.py
phiphadl/exceptionHandler/TrainingExceptionHandler.py
phiphadl/exceptionHandler/__init__.py
phiphadl/utils/LoggerColorFormatter.py
phiphadl/utils/__init__.py
phiphadl-0.1.4.dist-info/METADATA
phiphadl-0.1.4.dist-info/WHEEL
phiphadl-0.1.4.dist-info/top_level.txt
phiphadl-0.1.4.dist-info/RECORD
