Metadata-Version: 2.2
Name: phiphadl
Version: 0.1.4
Summary: Deep learning training and testing pipelines
Requires-Dist: torch
Requires-Dist: numpy
Requires-Dist: matplotlib
Requires-Dist: seaborn
Requires-Dist: scikit-learn
Dynamic: description
Dynamic: description-content-type
Dynamic: requires-dist
Dynamic: summary
